[
  {
   "title": "Gloves",
   "description": "The beautiful range of Apple Naturalé that has an exciting mix of natural ingredients. With the Goodness of 100% Natural Ingredients",
   "code": "GL",
   "price": "577.00",
   "status": true,
   "stock": 78722,
   "category": "Kids",
   "thumbnails": [],
   "_id": "1"
  },
  {
   "title": "Mouse",
   "description": "Ergonomic executive chair upholstered in bonded black leather and PVC padded seat and back for all-day comfort and support",
   "code": "JP",
   "price": "975.00",
   "status": false,
   "stock": 87974,
   "category": "Garden",
   "thumbnails": [],
   "_id": "2"
  },
  {
   "title": "Towels",
   "description": "New ABC 13 9370, 13.3, 5th Gen CoreA5-8250U, 8GB RAM, 256GB SSD, power UHD Graphics, OS 10 Home, OS Office A & J 2016",
   "code": "BY",
   "price": "140.00",
   "status": true,
   "stock": 53406,
   "category": "Games",
   "thumbnails": [],
   "_id": "3"
  },
  {
   "title": "Car",
   "description": "The Football Is Good For Training And Recreational Purposes",
   "code": "TD",
   "price": "563.00",
   "status": false,
   "stock": 26415,
   "category": "Computers",
   "thumbnails": [],
   "_id": "4"
  },
  {
   "title": "Chips",
   "description": "The beautiful range of Apple Naturalé that has an exciting mix of natural ingredients. With the Goodness of 100% Natural Ingredients",
   "code": "AE",
   "price": "910.00",
   "status": false,
   "stock": 50416,
   "category": "Music",
   "thumbnails": [],
   "_id": "5"
  },
  {
   "title": "Cheese",
   "description": "The Football Is Good For Training And Recreational Purposes",
   "code": "TO",
   "price": "860.00",
   "status": true,
   "stock": 39208,
   "category": "Clothing",
   "thumbnails": [],
   "_id": "6"
  },
  {
   "title": "Pizza",
   "description": "Ergonomic executive chair upholstered in bonded black leather and PVC padded seat and back for all-day comfort and support",
   "code": "TC",
   "price": "600.00",
   "status": true,
   "stock": 87887,
   "category": "Health",
   "thumbnails": [],
   "_id": "7"
  },
  {
   "title": "Pizza",
   "description": "Carbonite web goalkeeper gloves are ergonomically designed to give easy fit",
   "code": "PS",
   "price": "659.00",
   "status": true,
   "stock": 57218,
   "category": "Garden",
   "thumbnails": [],
   "_id": "8"
  },
  {
   "title": "Sausages",
   "description": "New range of formal shirts are designed keeping you in mind. With fits and styling that will make you stand apart",
   "code": "UG",
   "price": "589.00",
   "status": false,
   "stock": 17515,
   "category": "Games",
   "thumbnails": [],
   "_id": "9"
  },
  {
   "title": "Table",
   "description": "New ABC 13 9370, 13.3, 5th Gen CoreA5-8250U, 8GB RAM, 256GB SSD, power UHD Graphics, OS 10 Home, OS Office A & J 2016",
   "code": "AR",
   "price": "907.00",
   "status": true,
   "stock": 70878,
   "category": "Toys",
   "thumbnails": [],
   "_id": "10"
  },
  {
   "title": "Sausages",
   "description": "The beautiful range of Apple Naturalé that has an exciting mix of natural ingredients. With the Goodness of 100% Natural Ingredients",
   "code": "VN",
   "price": "104.00",
   "status": true,
   "stock": 26765,
   "category": "Sports",
   "thumbnails": [],
   "_id": "11"
  },
  {
   "title": "Table",
   "description": "The slim & simple Maple Gaming Keyboard from Dev Byte comes with a sleek body and 7- Color RGB LED Back-lighting for smart functionality",
   "code": "NC",
   "price": "239.00",
   "status": true,
   "stock": 6391,
   "category": "Automotive",
   "thumbnails": [],
   "_id": "12"
  },
  {
   "title": "Car",
   "description": "The beautiful range of Apple Naturalé that has an exciting mix of natural ingredients. With the Goodness of 100% Natural Ingredients",
   "code": "GI",
   "price": "655.00",
   "status": true,
   "stock": 31245,
   "category": "Garden",
   "thumbnails": [],
   "_id": "13"
  },
  {
   "title": "Chips",
   "description": "Boston's most advanced compression wear technology increases muscle oxygenation, stabilizes active muscles",
   "code": "SK",
   "price": "471.00",
   "status": false,
   "stock": 11058,
   "category": "Outdoors",
   "thumbnails": [],
   "_id": "14"
  },
  {
   "title": "Shirt",
   "description": "Boston's most advanced compression wear technology increases muscle oxygenation, stabilizes active muscles",
   "code": "SR",
   "price": "177.00",
   "status": false,
   "stock": 80972,
   "category": "Automotive",
   "thumbnails": [],
   "_id": "15"
  },
  {
   "title": "Chips",
   "description": "The Nagasaki Lander is the trademarked name of several series of Nagasaki sport bikes, that started with the 1984 ABC800J",
   "code": "IN",
   "price": "378.00",
   "status": true,
   "stock": 73549,
   "category": "Kids",
   "thumbnails": [],
   "_id": "16"
  },
  {
   "title": "Ball",
   "description": "Carbonite web goalkeeper gloves are ergonomically designed to give easy fit",
   "code": "KW",
   "price": "709.00",
   "status": true,
   "stock": 8577,
   "category": "Sports",
   "thumbnails": [],
   "_id": "17"
  },
  {
   "title": "Chips",
   "description": "The Football Is Good For Training And Recreational Purposes",
   "code": "SK",
   "price": "477.00",
   "status": false,
   "stock": 28213,
   "category": "Outdoors",
   "thumbnails": [],
   "_id": "18"
  },
  {
   "title": "Chair",
   "description": "The beautiful range of Apple Naturalé that has an exciting mix of natural ingredients. With the Goodness of 100% Natural Ingredients",
   "code": "RW",
   "price": "370.00",
   "status": false,
   "stock": 82236,
   "category": "Kids",
   "thumbnails": [],
   "_id": "19"
  },
  {
   "title": "Table",
   "description": "The Football Is Good For Training And Recreational Purposes",
   "code": "MY",
   "price": "362.00",
   "status": true,
   "stock": 40071,
   "category": "Home",
   "thumbnails": [],
   "_id": "20"
  },
  {
   "title": "Sausages",
   "description": "Carbonite web goalkeeper gloves are ergonomically designed to give easy fit",
   "code": "CI",
   "price": "809.00",
   "status": false,
   "stock": 81258,
   "category": "Garden",
   "thumbnails": [],
   "_id": "21"
  },
  {
   "title": "Sausages",
   "description": "The beautiful range of Apple Naturalé that has an exciting mix of natural ingredients. With the Goodness of 100% Natural Ingredients",
   "code": "PL",
   "price": "664.00",
   "status": false,
   "stock": 7031,
   "category": "Electronics",
   "thumbnails": [],
   "_id": "22"
  },
  {
   "title": "Tuna",
   "description": "New range of formal shirts are designed keeping you in mind. With fits and styling that will make you stand apart",
   "code": "AD",
   "price": "872.00",
   "status": true,
   "stock": 86138,
   "category": "Music",
   "thumbnails": [],
   "_id": "23"
  },
  {
   "title": "Hat",
   "description": "The Football Is Good For Training And Recreational Purposes",
   "code": "SS",
   "price": "627.00",
   "status": false,
   "stock": 6481,
   "category": "Movies",
   "thumbnails": [],
   "_id": "24"
  },
  {
   "title": "Chair",
   "description": "Carbonite web goalkeeper gloves are ergonomically designed to give easy fit",
   "code": "SV",
   "price": "559.00",
   "status": false,
   "stock": 27982,
   "category": "Baby",
   "thumbnails": [],
   "_id": "25"
  }
 ]